Metadata-Version: 2.1
Name: radio-browser
Version: 0.0.1
Summary: www.radio-browser.info api
Home-page: https://github.com/OpenJarbas/radio_browser
Author: JarbasAi
License: Apache2
Platform: UNKNOWN
